taskflux/__init__.py
taskflux/ameta/__init__.py
taskflux/ameta/abcmeta.py
taskflux/ameta/key.py
taskflux/cipher/__init__.py
taskflux/cipher/rsa.py
taskflux/databases/__init__.py
taskflux/databases/mongo_api.py
taskflux/databases/mongo_client.py
taskflux/generateId/__init__.py
taskflux/generateId/snowflake.py
taskflux/interface/__init__.py
taskflux/interface/interface.py
taskflux/logger/__init__.py
taskflux/logger/logger.py
taskflux/main/__init__.py
taskflux/main/build.py
taskflux/main/main.py
taskflux/main/run_server.py
taskflux/main/run_worker.py
taskflux/queue/__init__.py
taskflux/queue/rabbitmq.py
taskflux/rpc_proxy/__init__.py
taskflux/rpc_proxy/client.py
taskflux/rpc_proxy/decorator.py
taskflux/rpc_proxy/rpc_proxy.py
taskflux/system_services/__init__.py
taskflux/system_services/monitoring/__init__.py
taskflux/system_services/monitoring/heartbeat_detection.py
taskflux/system_services/monitoring/system_info.py
taskflux/system_services/schedule/__init__.py
taskflux/system_services/schedule/run_schedule.py
taskflux/system_services/schedule/task_distribution.py
taskflux/utils/__init__.py
taskflux/utils/network.py
taskflux/utils/parser.py
taskflux/utils/timeformat.py
TaskFlux-1.1.1.dist-info/METADATA
TaskFlux-1.1.1.dist-info/WHEEL
TaskFlux-1.1.1.dist-info/top_level.txt
TaskFlux-1.1.1.dist-info/RECORD
