Metadata-Version: 2.2
Name: TaskFlux
Version: 1.1.1
Summary: TaskFlux Description
Home-page: https://gitee.com/ZYPH/pyrpc-schedule
Author: YanPing
Author-email: zyphhxx@foxmail.com
Maintainer: YanPing
Maintainer-email: zyphhxx@foxmail.com
License: MIT License
Classifier: Development Status :: 3 - Alpha
Classifier: Intended Audience :: Developers
Classifier: Topic :: Software Development :: Build Tools
Classifier: License :: OSI Approved :: MIT License
Classifier: Programming Language :: Python :: 3
Requires-Python: >=3.9
Requires-Dist: amqp
Requires-Dist: eventlet
Requires-Dist: kombu
Requires-Dist: pika
Requires-Dist: pytz
Requires-Dist: psutil
Requires-Dist: pycryptodomex
Requires-Dist: pymongo
Dynamic: author
Dynamic: author-email
Dynamic: classifier
Dynamic: description
Dynamic: home-page
Dynamic: license
Dynamic: maintainer
Dynamic: maintainer-email
Dynamic: requires-dist
Dynamic: requires-python
Dynamic: summary
